iotflows/__init__.py
iotflows/realtime.py
iotflows-1.1.11.dist-info/LICENSE
iotflows-1.1.11.dist-info/METADATA
iotflows-1.1.11.dist-info/WHEEL
iotflows-1.1.11.dist-info/top_level.txt
iotflows-1.1.11.dist-info/RECORD
