Metadata-Version: 2.1
Name: iotflows
Version: 1.1.11
Summary: IoTFlows Open Source Python WebSocket SDK.
Home-page: https://github.com/iotflows/iotflows-python
Author: IoTFLows Inc
Author-email: info@iotflows.com
License: Apache License 2.0
Platform: UNKNOWN
Requires-Dist: pathlib2
Requires-Dist: setuptools
Requires-Dist: paho-mqtt
Requires-Dist: requests
